clean_df/__init__.py
clean_df/clean_df.py
clean_df/utils.py
clean_df-0.3.0.dist-info/AUTHORS.rst
clean_df-0.3.0.dist-info/LICENSE
clean_df-0.3.0.dist-info/METADATA
clean_df-0.3.0.dist-info/WHEEL
clean_df-0.3.0.dist-info/top_level.txt
clean_df-0.3.0.dist-info/RECORD
