Metadata-Version: 2.1
Name: clean-df
Version: 0.3.0
Summary: Python module to report, clean, and optimize Pandas Dataframes effectively
Home-page: https://github.com/naelaqel/clean_df
Author: Nael Aqel
Author-email: dev@naelaqel.com
License: MIT license
Keywords: clean_df,cleaning,data analysis,data science,wrangling,reporting,optimization,outliers,missing
Classifier: Development Status :: 2 - Pre-Alpha
Classifier: Intended Audience :: Developers
Classifier: License :: OSI Approved :: MIT License
Classifier: Natural Language :: English
Classifier: Programming Language :: Python :: 3
Classifier: Programming Language :: Python :: 3.7
Classifier: Programming Language :: Python :: 3.8
Classifier: Programming Language :: Python :: 3.9
Classifier: Programming Language :: Python :: 3.10
Classifier: Programming Language :: Python :: 3.11
Requires-Python: >=3.7
License-File: LICENSE
License-File: AUTHORS.rst
Requires-Dist: missingno >=0.4.1
Requires-Dist: numpy >=1.19.3
Requires-Dist: pandas >=0.25.3
Requires-Dist: IPython >=7.10
Requires-Dist: matplotlib >=3.0.3
Requires-Dist: tabulate >=0.8.0
Requires-Dist: scikit-image >=0.15.0
